oarc_crawlers/__init__.py
oarc_crawlers/main.py
oarc_crawlers/api/__init__.py
oarc_crawlers/cli/__init__.py
oarc_crawlers/cli/help_texts.py
oarc_crawlers/config/__init__.py
oarc_crawlers/config/config.py
oarc_crawlers/config/config_editor.py
oarc_crawlers/config/config_manager.py
oarc_crawlers/config/config_validators.py
oarc_crawlers/core/__init__.py
oarc_crawlers/core/crawlers/__init__.py
oarc_crawlers/core/crawlers/arxiv_crawler.py
oarc_crawlers/core/crawlers/ddg_crawler.py
oarc_crawlers/core/crawlers/gh_crawler.py
oarc_crawlers/core/crawlers/oeis_crawler.py
oarc_crawlers/core/crawlers/web_crawler.py
oarc_crawlers/core/crawlers/yt_crawler.py
oarc_crawlers/core/mcp/__init__.py
oarc_crawlers/core/mcp/mcp_manager.py
oarc_crawlers/core/mcp/mcp_server.py
oarc_crawlers/core/storage/__init__.py
oarc_crawlers/core/storage/parquet_storage.py
oarc_crawlers/utils/__init__.py
oarc_crawlers/utils/build_utils.py
oarc_crawlers/utils/const.py
oarc_crawlers/utils/crawler_utils.py
oarc_crawlers/utils/mcp_utils.py
oarc_crawlers/utils/paths.py
oarc_crawlers/utils/storage_utils.py
oarc_crawlers-0.1.14.dist-info/licenses/LICENSE
oarc_crawlers-0.1.14.dist-info/METADATA
oarc_crawlers-0.1.14.dist-info/WHEEL
oarc_crawlers-0.1.14.dist-info/entry_points.txt
oarc_crawlers-0.1.14.dist-info/top_level.txt
oarc_crawlers-0.1.14.dist-info/RECORD
