Metadata-Version: 2.4
Name: oarc-crawlers
Version: 0.1.14
Summary: A modular, async Python framework for structured online data collection used by Ollama Agent Roll Cage (OARC)
Author: OARC Team
License-Expression: Apache-2.0
Project-URL: Homepage, https://github.com/Ollama-Agent-Roll-Cage/oarc-crawlers
Project-URL: Bug Tracker, https://github.com/Ollama-Agent-Roll-Cage/oarc-crawlers/issues
Classifier: Development Status :: 4 - Beta
Classifier: Intended Audience :: Developers
Classifier: Programming Language :: Python :: 3
Classifier: Programming Language :: Python :: 3.10
Classifier: Programming Language :: Python :: 3.11
Classifier: Programming Language :: Python :: 3.12
Classifier: Programming Language :: Python :: 3.13
Requires-Python: >=3.10
License-File: LICENSE
Requires-Dist: aiohttp>=3.11.18
Requires-Dist: arxiv>=2.2.0
Requires-Dist: beautifulsoup4>=4.13.4
Requires-Dist: click>=8.1.8
Requires-Dist: duckduckgo-search>=8.0.1
Requires-Dist: fastmcp>=2.2.2
Requires-Dist: gitpython>=3.1.44
Requires-Dist: llama-index-experimental>=0.5.5
Requires-Dist: moviepy>=2.1.2
Requires-Dist: mypy>=1.15.0
Requires-Dist: oarc-log>=0.1.1
Requires-Dist: oarc-utils>=0.1.1
Requires-Dist: pandas>=2.2.3
Requires-Dist: psutil>=7.0.0
Requires-Dist: pyarrow>=19.0.1
Requires-Dist: pygithub>=2.6.1
Requires-Dist: pyinstaller>=6.13.0
Requires-Dist: pytchat>=0.5.5
Requires-Dist: pytube>=15.0.0
Requires-Dist: questionary>=2.1.0
Requires-Dist: types-beautifulsoup4>=4.12.0.20250204
Requires-Dist: websockets>=15.0.1
Requires-Dist: magika>=0.6.2
Requires-Dist: onnxruntime>=1.21.1
Requires-Dist: numpy>=2.2.5
Provides-Extra: dev
Requires-Dist: black>=25.1.0; extra == "dev"
Requires-Dist: build>=1.2.2.post1; extra == "dev"
Requires-Dist: isort>=6.0.1; extra == "dev"
Requires-Dist: pytest>=8.3.5; extra == "dev"
Requires-Dist: pytest-asyncio>=0.26.0; extra == "dev"
Requires-Dist: pytest-cov>=6.1.1; extra == "dev"
Requires-Dist: ruff>=0.11.6; extra == "dev"
Requires-Dist: twine>=6.1.0; extra == "dev"
Requires-Dist: PyQt6>=6.9.0; extra == "dev"
Requires-Dist: pyvis>=0.3.2; extra == "dev"
Requires-Dist: PyQt6-WebEngine>=6.9.0; extra == "dev"
Dynamic: license-file
